{"name":"Ti","tagline":"notatki do przedmiotu technologie internetowe","body":"#Notatki do Technologii internetowych\r\n<blockquote><p><i> dzień bez kodowanoa jest dniem straconym<\\i>\r\nZnaczniki:\r\n\r\n* p\r\n* ul, ol\r\n* li\r\n* img\r\n* h\r\n* \r\n```html\r\n<!doctype html>\r\n<html lang=pl>\r\n<head>\r\n  <meta charset=utf-8>\r\n  <title>Szablon strony HTML5</title>\r\n</head>\r\n<body>\r\n  <p>ąćęłńóśźż ĄĆĘŁŃÓŚŹŻ</p>\r\n<p>ąćęłńóśźż ĄĆĘŁŃÓŚŹŻ</p>\r\n</body>\r\n</html>\r\n```\r\n \"Jak prezydent nie obroni ministra Gowina, to już go nie ma\"\r\nSikorski: <br>\r\n--MSZ nie zainterweniuje ws. obrażania Radwańskich\r\nnowe Prokuratura umorzyła śledztwo w sprawie syna premiera \r\n\r\n\r\n**ala**ma kola \r\n\r\n\r\n------------\r\n\r\n_ola_ ma psa\r\n\r\n\r\n[elementarz polskiego](http://www.gazeta.pl/0,0.html)\r\n\r\n![alt text](http://czasy-prl.za.pl/images/photoalbum/elementarz_0.jpg)\r\nfast scrol","google":"","note":"Don't delete this file! It's used internally to help with page regeneration."}